dashai_test_text_classification_package/__init__.py
dashai_test_text_classification_package/bow_text_classification_model.py
dashai_test_text_classification_package/text_classification_model.py
dashai_test_text_classification_package/text_classification_task.py
dashai_test_text_classification_package-0.0.6.dist-info/METADATA
dashai_test_text_classification_package-0.0.6.dist-info/WHEEL
dashai_test_text_classification_package-0.0.6.dist-info/entry_points.txt
dashai_test_text_classification_package-0.0.6.dist-info/RECORD
